Metadata-Version: 2.1
Name: datalama
Version: 1.0.0
Summary: Datalama client, for Python 3.
Home-page: https://datalama.io
Author: Datalama
Author-email: support@datalama.io
License: MIT
Keywords: tiktok api,tiktok-api,tiktok
Classifier: Development Status :: 4 - Beta
Classifier: Intended Audience :: Developers
Classifier: License :: OSI Approved :: MIT License
Classifier: Topic :: Software Development :: Libraries :: Python Modules
Classifier: Programming Language :: Python :: 3.8
Classifier: Programming Language :: Python :: 3.9
Classifier: Programming Language :: Python :: 3.10
Classifier: Programming Language :: Python :: 3.11
Requires-Python: >=3.8
